XplainML/__init__.py
XplainML/explainability.py
XplainML/responsible_ai.py
XplainML-0.0.1.dist-info/LICENSE
XplainML-0.0.1.dist-info/METADATA
XplainML-0.0.1.dist-info/WHEEL
XplainML-0.0.1.dist-info/top_level.txt
XplainML-0.0.1.dist-info/RECORD
