Metadata-Version: 2.1
Name: XplainML
Version: 0.0.1
Summary: XplainML is a comprehensive Python package designed for Explainable AI (XAI) and Responsible AI practices. It provides a suite of tools and algorithms to enhance the transparency, interpretability, and fairness of machine learning models.
Home-page: https://github.com/DeependraVerma/XAI_ResponsibleAI_Toolbox
Author: DeependraVerma
Author-email: deependra.verma00@gmail.com
License: MIT
Project-URL: Bug Tracker, https://github.com/DeependraVerma/XAI_ResponsibleAI_Toolbox/issues
Classifier: Programming Language :: Python :: 3.7
Classifier: Programming Language :: Python :: 3.8
Classifier: Programming Language :: Python :: 3.9
Classifier: Operating System :: OS Independent
License-File: LICENSE
Requires-Dist: pandas
Requires-Dist: numpy
Requires-Dist: scikit-learn
Requires-Dist: shap
Requires-Dist: lime
Requires-Dist: aif360
Requires-Dist: fairlearn
Requires-Dist: seaborn
Requires-Dist: matplotlib
Requires-Dist: scikit-image
Provides-Extra: testing
Requires-Dist: tox ==3.25.1 ; extra == 'testing'
Requires-Dist: tox-gh-actions ; extra == 'testing'
Requires-Dist: pytest >=7.1.3 ; extra == 'testing'
Requires-Dist: black >=22.8.0 ; extra == 'testing'
Requires-Dist: flake8 >=5.0.4 ; extra == 'testing'
Requires-Dist: mypy >=0.971 ; extra == 'testing'
